[
  {
    "musical": "Wicked",
    "urls": [
      "https://wickedelmusical.com/",
      "https://wickedelmusical.com/elenco",
      "https://tickets.wickedelmusical.com/espectaculo/wicked-el-musical/W01"
    ]
  },
  {
    "musical": "Houdini",
    "urls": [
      "https://www.houdinielmusical.com"
    ]
  },
  {
    "musical": "Los Miserables",
    "urls": [
      "https://miserableselmusical.es/",
      "https://miserableselmusical.es/elenco",
      "https://tickets.miserableselmusical.es/espectaculo/los-miserables/M01"
    ]
  },
  {
    "musical": "The Book of Mormon",
    "urls": [
      "https://thebookofmormonelmusical.es",
      "https://thebookofmormonelmusical.es/elenco/",
      "https://tickets.thebookofmormonelmusical.es/espectaculo/the-book-of-mormon-el-musical/BM01"
    ]
  },
  {
  "musical": "httpbin (prueba)",
    "urls": [
      "https://httpbin.org/get"
    ],
    "hidden": true
  }
]

